qrs_api_client/__init__.py
qrs_api_client/auth.py
qrs_api_client/client.py
qrs_api_client/models.py
qrs_api_client-2.1.0.dist-info/LICENSE
qrs_api_client-2.1.0.dist-info/METADATA
qrs_api_client-2.1.0.dist-info/WHEEL
qrs_api_client-2.1.0.dist-info/top_level.txt
qrs_api_client-2.1.0.dist-info/RECORD
