Metadata-Version: 2.1
Name: qrs-api-client
Version: 2.1.0
Summary: Python client for Qlik Sense Repository Service API.
Home-page: https://github.com/rumen-vasilev/qrs-api-client
Author: Rumen Vasilev
Author-email: rumen.vasilev@gmail.com
License: Apache 2.0
Classifier: Programming Language :: Python :: 3
Classifier: License :: OSI Approved :: MIT License
Classifier: Operating System :: OS Independent
Requires-Python: >=3.6
License-File: LICENSE
Requires-Dist: requests>=2.32.3
Requires-Dist: requests_ntlm>=1.2.0
Requires-Dist: python-dotenv>=1.0.0
